odoo/addons/crm_partner_assign/README.rst
odoo/addons/crm_partner_assign/__init__.py
odoo/addons/crm_partner_assign/__manifest__.py
odoo/addons/crm_partner_assign/i18n/crm_partner_assign.pot
odoo/addons/crm_partner_assign/i18n/es.po
odoo/addons/crm_partner_assign/i18n/it.po
odoo/addons/crm_partner_assign/i18n/tr.po
odoo/addons/crm_partner_assign/models/__init__.py
odoo/addons/crm_partner_assign/models/crm_lead.py
odoo/addons/crm_partner_assign/models/res_partner.py
odoo/addons/crm_partner_assign/readme/CONTRIBUTORS.md
odoo/addons/crm_partner_assign/readme/CREDITS.md
odoo/addons/crm_partner_assign/readme/DESCRIPTION.md
odoo/addons/crm_partner_assign/readme/INSTALL.md
odoo/addons/crm_partner_assign/readme/USAGE.md
odoo/addons/crm_partner_assign/static/description/icon.png
odoo/addons/crm_partner_assign/static/description/index.html
odoo/addons/crm_partner_assign/tests/__init__.py
odoo/addons/crm_partner_assign/tests/test_crm_lead.py
odoo/addons/crm_partner_assign/views/crm_lead_view.xml
odoo/addons/crm_partner_assign/views/res_partner_view.xml
odoo_addon_crm_partner_assign-18.0.1.0.0.3.dist-info/METADATA
odoo_addon_crm_partner_assign-18.0.1.0.0.3.dist-info/WHEEL
odoo_addon_crm_partner_assign-18.0.1.0.0.3.dist-info/top_level.txt
odoo_addon_crm_partner_assign-18.0.1.0.0.3.dist-info/RECORD
